{
    "key": "group_inlife_society_landing",
    "title": "InLife – Society Landing",
    "fields": [
        {
            "key": "field_society_landing_tab_hero",
            "label": "Hero",
            "name": "",
            "aria-label": "",
            "type": "tab",
            "instructions": "",
            "required": 0,
            "conditional_logic": 0,
            "wrapper": {
                "width": "",
                "class": "",
                "id": ""
            },
            "placement": "top",
            "endpoint": 0,
            "selected": 0
        },
        {
            "key": "field_society_hero_kicker",
            "label": "Hero kicker",
            "name": "society_hero_kicker",
            "aria-label": "",
            "type": "text",
            "instructions": "Short label above the title, e.g. SPOŁECZEŃSTWO.",
            "required": 0,
            "conditional_logic": 0,
            "wrapper": {
                "width": "33",
                "class": "",
                "id": ""
            },
            "default_value": "SPOŁECZEŃSTWO",
            "maxlength": 80,
            "allow_in_bindings": 0,
            "placeholder": "",
            "prepend": "",
            "append": ""
        },
        {
            "key": "field_society_hero_title",
            "label": "Hero title",
            "name": "society_hero_title",
            "aria-label": "",
            "type": "text",
            "instructions": "Main H1 for the Society landing page.",
            "required": 1,
            "conditional_logic": 0,
            "wrapper": {
                "width": "67",
                "class": "",
                "id": ""
            },
            "default_value": "",
            "maxlength": 120,
            "allow_in_bindings": 0,
            "placeholder": "",
            "prepend": "",
            "append": ""
        },
        {
            "key": "field_society_hero_lead",
            "label": "Hero lead",
            "name": "society_hero_lead",
            "aria-label": "",
            "type": "textarea",
            "instructions": "Lead paragraph under the title.",
            "required": 0,
            "conditional_logic": 0,
            "wrapper": {
                "width": "100",
                "class": "",
                "id": ""
            },
            "default_value": "",
            "maxlength": "",
            "rows": 3,
            "placeholder": "",
            "new_lines": "br"
        },
        {
            "key": "field_society_hero_primary_cta_group",
            "label": "Primary CTA",
            "name": "society_hero_primary_cta",
            "aria-label": "",
            "type": "group",
            "instructions": "Optional primary button in the hero.",
            "required": 0,
            "conditional_logic": 0,
            "wrapper": {
                "width": "50",
                "class": "",
                "id": ""
            },
            "layout": "block",
            "sub_fields": [
                {
                    "key": "field_society_hero_primary_cta_label",
                    "label": "Label",
                    "name": "label",
                    "aria-label": "",
                    "type": "text",
                    "instructions": "",
                    "required": 0,
                    "conditional_logic": false,
                    "wrapper": {
                        "width": "50",
                        "class": "",
                        "id": ""
                    },
                    "default_value": "",
                    "maxlength": 60,
                    "allow_in_bindings": 0,
                    "placeholder": "",
                    "prepend": "",
                    "append": ""
                },
                {
                    "key": "field_society_hero_primary_cta_url",
                    "label": "URL",
                    "name": "url",
                    "aria-label": "",
                    "type": "url",
                    "instructions": "",
                    "required": 0,
                    "conditional_logic": false,
                    "wrapper": {
                        "width": "50",
                        "class": "",
                        "id": ""
                    },
                    "default_value": "",
                    "placeholder": ""
                }
            ]
        },
        {
            "key": "field_society_hero_secondary_cta_group",
            "label": "Secondary CTA",
            "name": "society_hero_secondary_cta",
            "aria-label": "",
            "type": "group",
            "instructions": "Optional secondary button in the hero.",
            "required": 0,
            "conditional_logic": 0,
            "wrapper": {
                "width": "50",
                "class": "",
                "id": ""
            },
            "layout": "block",
            "sub_fields": [
                {
                    "key": "field_society_hero_secondary_cta_label",
                    "label": "Label",
                    "name": "label",
                    "aria-label": "",
                    "type": "text",
                    "instructions": "",
                    "required": 0,
                    "conditional_logic": false,
                    "wrapper": {
                        "width": "50",
                        "class": "",
                        "id": ""
                    },
                    "default_value": "",
                    "maxlength": 60,
                    "allow_in_bindings": 0,
                    "placeholder": "",
                    "prepend": "",
                    "append": ""
                },
                {
                    "key": "field_society_hero_secondary_cta_url",
                    "label": "URL",
                    "name": "url",
                    "aria-label": "",
                    "type": "url",
                    "instructions": "",
                    "required": 0,
                    "conditional_logic": false,
                    "wrapper": {
                        "width": "50",
                        "class": "",
                        "id": ""
                    },
                    "default_value": "",
                    "placeholder": ""
                }
            ]
        },
        {
            "key": "field_society_hero_media_group",
            "label": "Hero media",
            "name": "society_hero_media",
            "aria-label": "",
            "type": "group",
            "instructions": "Optional visual content shown in hero.",
            "required": 0,
            "conditional_logic": 0,
            "wrapper": {
                "width": "100",
                "class": "",
                "id": ""
            },
            "layout": "block",
            "sub_fields": [
                {
                    "key": "field_society_hero_image",
                    "label": "Image",
                    "name": "image",
                    "aria-label": "",
                    "type": "image",
                    "instructions": "Upload hero image. Remember meaningful alt text.",
                    "required": 0,
                    "conditional_logic": false,
                    "wrapper": {
                        "width": "34",
                        "class": "",
                        "id": ""
                    },
                    "return_format": "array",
                    "library": "all",
                    "preview_size": "medium",
                    "min_width": "",
                    "min_height": "",
                    "min_size": "",
                    "max_width": "",
                    "max_height": "",
                    "max_size": "",
                    "mime_types": "jpg,jpeg,png,webp,svg"
                },
                {
                    "key": "field_society_hero_video_embed",
                    "label": "Video embed URL",
                    "name": "video_embed_url",
                    "aria-label": "",
                    "type": "oembed",
                    "instructions": "Optional YouTube\/Vimeo link if hero should show video instead of image.",
                    "required": 0,
                    "conditional_logic": false,
                    "wrapper": {
                        "width": "33",
                        "class": "",
                        "id": ""
                    },
                    "width": "",
                    "height": ""
                },
                {
                    "key": "field_society_hero_media_caption",
                    "label": "Caption \/ note",
                    "name": "caption",
                    "aria-label": "",
                    "type": "text",
                    "instructions": "Optional short supporting text near the media.",
                    "required": 0,
                    "conditional_logic": false,
                    "wrapper": {
                        "width": "33",
                        "class": "",
                        "id": ""
                    },
                    "default_value": "",
                    "maxlength": 140,
                    "allow_in_bindings": 0,
                    "placeholder": "",
                    "prepend": "",
                    "append": ""
                }
            ]
        },
        {
            "key": "field_society_landing_tab_science",
            "label": "Science for you",
            "name": "",
            "aria-label": "",
            "type": "tab",
            "instructions": "",
            "required": 0,
            "conditional_logic": 0,
            "wrapper": {
                "width": "",
                "class": "",
                "id": ""
            },
            "placement": "top",
            "endpoint": 0,
            "selected": 0
        },
        {
            "key": "field_society_science_section_enabled",
            "label": "Show section",
            "name": "society_science_section_enabled",
            "aria-label": "",
            "type": "true_false",
            "instructions": "Toggle the whole ‘Nauka dla Ciebie’ block.",
            "required": 0,
            "conditional_logic": 0,
            "wrapper": {
                "width": "25",
                "class": "",
                "id": ""
            },
            "message": "Enable Science for you section",
            "default_value": 1,
            "ui": 1,
            "ui_on_text": "Show",
            "ui_off_text": "Hide"
        },
        {
            "key": "field_society_science_title",
            "label": "Section title",
            "name": "society_science_title",
            "aria-label": "",
            "type": "text",
            "instructions": "",
            "required": 0,
            "conditional_logic": [
                [
                    {
                        "field": "field_society_science_section_enabled",
                        "operator": "==",
                        "value": "1"
                    }
                ]
            ],
            "wrapper": {
                "width": "75",
                "class": "",
                "id": ""
            },
            "default_value": "Nauka dla Ciebie",
            "maxlength": 120,
            "allow_in_bindings": 0,
            "placeholder": "",
            "prepend": "",
            "append": ""
        },
        {
            "key": "field_society_science_content",
            "label": "Main content",
            "name": "society_science_content",
            "aria-label": "",
            "type": "wysiwyg",
            "instructions": "Main editorial description. Can contain lists and links.",
            "required": 0,
            "conditional_logic": [
                [
                    {
                        "field": "field_society_science_section_enabled",
                        "operator": "==",
                        "value": "1"
                    }
                ]
            ],
            "wrapper": {
                "width": "100",
                "class": "",
                "id": ""
            },
            "default_value": "",
            "tabs": "all",
            "toolbar": "full",
            "media_upload": 1,
            "delay": 0
        },
        {
            "key": "field_society_science_media_type",
            "label": "Media type",
            "name": "society_science_media_type",
            "aria-label": "",
            "type": "button_group",
            "instructions": "Choose what accompanies the section content.",
            "required": 0,
            "conditional_logic": [
                [
                    {
                        "field": "field_society_science_section_enabled",
                        "operator": "==",
                        "value": "1"
                    }
                ]
            ],
            "wrapper": {
                "width": "34",
                "class": "",
                "id": ""
            },
            "choices": {
                "image": "Image",
                "video": "Video",
                "none": "None"
            },
            "default_value": "image",
            "return_format": "value",
            "allow_null": 0,
            "layout": "horizontal"
        },
        {
            "key": "field_society_science_image",
            "label": "Image",
            "name": "society_science_image",
            "aria-label": "",
            "type": "image",
            "instructions": "",
            "required": 0,
            "conditional_logic": [
                [
                    {
                        "field": "field_society_science_section_enabled",
                        "operator": "==",
                        "value": "1"
                    },
                    {
                        "field": "field_society_science_media_type",
                        "operator": "==",
                        "value": "image"
                    }
                ]
            ],
            "wrapper": {
                "width": "33",
                "class": "",
                "id": ""
            },
            "return_format": "array",
            "library": "all",
            "preview_size": "medium",
            "mime_types": "jpg,jpeg,png,webp,svg",
            "min_width": 0,
            "min_height": 0,
            "min_size": 0,
            "max_width": 0,
            "max_height": 0,
            "max_size": 0
        },
        {
            "key": "field_society_science_video",
            "label": "Video embed URL",
            "name": "society_science_video",
            "aria-label": "",
            "type": "oembed",
            "instructions": "",
            "required": 0,
            "conditional_logic": [
                [
                    {
                        "field": "field_society_science_section_enabled",
                        "operator": "==",
                        "value": "1"
                    },
                    {
                        "field": "field_society_science_media_type",
                        "operator": "==",
                        "value": "video"
                    }
                ]
            ],
            "wrapper": {
                "width": "33",
                "class": "",
                "id": ""
            },
            "width": "",
            "height": ""
        },
        {
            "key": "field_society_science_cta_group",
            "label": "Section CTA",
            "name": "society_science_cta",
            "aria-label": "",
            "type": "group",
            "instructions": "Optional button below the content.",
            "required": 0,
            "conditional_logic": [
                [
                    {
                        "field": "field_society_science_section_enabled",
                        "operator": "==",
                        "value": "1"
                    }
                ]
            ],
            "wrapper": {
                "width": "33",
                "class": "",
                "id": ""
            },
            "layout": "block",
            "sub_fields": [
                {
                    "key": "field_society_science_cta_label",
                    "label": "Label",
                    "name": "label",
                    "aria-label": "",
                    "type": "text",
                    "instructions": "",
                    "required": false,
                    "conditional_logic": false,
                    "wrapper": {
                        "width": "50",
                        "class": "",
                        "id": ""
                    },
                    "maxlength": 60,
                    "allow_in_bindings": 0,
                    "default_value": "",
                    "placeholder": "",
                    "prepend": "",
                    "append": ""
                },
                {
                    "key": "field_society_science_cta_url",
                    "label": "URL",
                    "name": "url",
                    "aria-label": "",
                    "type": "url",
                    "instructions": "",
                    "required": false,
                    "conditional_logic": false,
                    "wrapper": {
                        "width": "50",
                        "class": "",
                        "id": ""
                    },
                    "default_value": "",
                    "placeholder": ""
                }
            ]
        },
        {
            "key": "field_society_landing_tab_articles",
            "label": "Articles",
            "name": "",
            "aria-label": "",
            "type": "tab",
            "instructions": "",
            "required": 0,
            "conditional_logic": 0,
            "wrapper": {
                "width": "",
                "class": "",
                "id": ""
            },
            "placement": "top",
            "endpoint": 0,
            "selected": 0
        },
        {
            "key": "field_society_articles_title",
            "label": "Section title",
            "name": "society_articles_title",
            "aria-label": "",
            "type": "text",
            "instructions": "",
            "required": 0,
            "conditional_logic": 0,
            "wrapper": {
                "width": "50",
                "class": "",
                "id": ""
            },
            "default_value": "Artykuły",
            "maxlength": 120,
            "allow_in_bindings": 0,
            "placeholder": "",
            "prepend": "",
            "append": ""
        },
        {
            "key": "field_society_articles_archive_page",
            "label": "Archive \/ all articles page",
            "name": "society_articles_archive_page",
            "aria-label": "",
            "type": "page_link",
            "instructions": "Select the page that will list all Society articles.",
            "required": 0,
            "conditional_logic": 0,
            "wrapper": {
                "width": "50",
                "class": "",
                "id": ""
            },
            "post_type": [
                "page"
            ],
            "post_status": [
                "publish",
                "draft"
            ],
            "taxonomy": "",
            "allow_null": 1,
            "multiple": 0,
            "allow_archives": 0
        },
        {
            "key": "field_society_articles_intro",
            "label": "Section intro",
            "name": "society_articles_intro",
            "aria-label": "",
            "type": "textarea",
            "instructions": "Optional short intro above article cards.",
            "required": 0,
            "conditional_logic": 0,
            "wrapper": {
                "width": "100",
                "class": "",
                "id": ""
            },
            "default_value": "",
            "maxlength": "",
            "rows": 2,
            "placeholder": "",
            "new_lines": "br"
        },
        {
            "key": "field_society_articles_mode",
            "label": "Landing content mode",
            "name": "society_articles_mode",
            "aria-label": "",
            "type": "button_group",
            "instructions": "Choose whether the landing shows manually selected posts or latest posts from Society taxonomy\/query.",
            "required": 0,
            "conditional_logic": 0,
            "wrapper": {
                "width": "34",
                "class": "",
                "id": ""
            },
            "choices": {
                "manual": "Manual selection",
                "latest": "Latest posts"
            },
            "default_value": "manual",
            "return_format": "value",
            "allow_null": 0,
            "layout": "horizontal"
        },
        {
            "key": "field_society_articles_count",
            "label": "Number of cards",
            "name": "society_articles_count",
            "aria-label": "",
            "type": "number",
            "instructions": "Recommended: 3 or 6.",
            "required": 0,
            "conditional_logic": 0,
            "wrapper": {
                "width": "33",
                "class": "",
                "id": ""
            },
            "default_value": 3,
            "min": 1,
            "max": 12,
            "step": 1,
            "placeholder": "",
            "prepend": "",
            "append": ""
        },
        {
            "key": "field_society_articles_show_badge",
            "label": "Show badge on cards",
            "name": "society_articles_show_badge",
            "aria-label": "",
            "type": "true_false",
            "instructions": "Badge should usually come from Society taxonomy term.",
            "required": 0,
            "conditional_logic": 0,
            "wrapper": {
                "width": "33",
                "class": "",
                "id": ""
            },
            "message": "Enable article badges",
            "default_value": 1,
            "ui": 1,
            "ui_on_text": "Show",
            "ui_off_text": "Hide"
        },
        {
            "key": "field_society_articles_manual_posts",
            "label": "Manual posts",
            "name": "society_articles_manual_posts",
            "aria-label": "",
            "type": "relationship",
            "instructions": "Pick posts to show on landing in desired order.",
            "required": 0,
            "conditional_logic": [
                [
                    {
                        "field": "field_society_articles_mode",
                        "operator": "==",
                        "value": "manual"
                    }
                ]
            ],
            "wrapper": {
                "width": "100",
                "class": "",
                "id": ""
            },
            "post_type": [
                "post"
            ],
            "post_status": [
                "publish",
                "draft"
            ],
            "taxonomy": "",
            "filters": [
                "search",
                "post_type",
                "taxonomy"
            ],
            "return_format": "object",
            "min": 0,
            "max": 12,
            "elements": [
                "featured_image"
            ],
            "bidirectional_target": []
        },
        {
            "key": "field_society_articles_latest_category_hint",
            "label": "Latest mode note",
            "name": "",
            "aria-label": "",
            "type": "message",
            "instructions": "",
            "required": 0,
            "conditional_logic": [
                [
                    {
                        "field": "field_society_articles_mode",
                        "operator": "==",
                        "value": "latest"
                    }
                ]
            ],
            "wrapper": {
                "width": "100",
                "class": "",
                "id": ""
            },
            "message": "Recommended implementation: query only posts marked for Society using your dedicated taxonomy\/terms, not all recent posts.",
            "new_lines": "wpautop",
            "esc_html": 0
        },
        {
            "key": "field_society_landing_tab_initiatives",
            "label": "Initiatives",
            "name": "",
            "aria-label": "",
            "type": "tab",
            "instructions": "",
            "required": 0,
            "conditional_logic": 0,
            "wrapper": {
                "width": "",
                "class": "",
                "id": ""
            },
            "placement": "top",
            "endpoint": 0,
            "selected": 0
        },
        {
            "key": "field_society_initiatives_title",
            "label": "Section title",
            "name": "society_initiatives_title",
            "aria-label": "",
            "type": "text",
            "instructions": "Recommended label: Projekty i inicjatywy.",
            "required": 0,
            "conditional_logic": 0,
            "wrapper": {
                "width": "50",
                "class": "",
                "id": ""
            },
            "default_value": "Projekty i inicjatywy",
            "maxlength": 120,
            "allow_in_bindings": 0,
            "placeholder": "",
            "prepend": "",
            "append": ""
        },
        {
            "key": "field_society_initiatives_intro",
            "label": "Section intro",
            "name": "society_initiatives_intro",
            "aria-label": "",
            "type": "textarea",
            "instructions": "Optional supporting text above the cards.",
            "required": 0,
            "conditional_logic": 0,
            "wrapper": {
                "width": "50",
                "class": "",
                "id": ""
            },
            "default_value": "",
            "maxlength": "",
            "rows": 2,
            "placeholder": "",
            "new_lines": "br"
        },
        {
            "key": "field_society_initiatives_pages",
            "label": "Initiative pages",
            "name": "society_initiatives_pages",
            "aria-label": "",
            "type": "relationship",
            "instructions": "Pick initiative pages to feature on the landing page.",
            "required": 0,
            "conditional_logic": 0,
            "wrapper": {
                "width": "100",
                "class": "",
                "id": ""
            },
            "post_type": [
                "page"
            ],
            "post_status": [
                "publish",
                "draft"
            ],
            "taxonomy": "",
            "filters": [
                "search",
                "post_type"
            ],
            "return_format": "object",
            "min": 0,
            "max": 12,
            "elements": [
                "featured_image"
            ],
            "bidirectional_target": []
        },
        {
            "key": "field_society_initiatives_archive_page",
            "label": "Optional ‘all initiatives’ page",
            "name": "society_initiatives_archive_page",
            "aria-label": "",
            "type": "page_link",
            "instructions": "Optional page for broader listing of initiatives.",
            "required": 0,
            "conditional_logic": 0,
            "wrapper": {
                "width": "50",
                "class": "",
                "id": ""
            },
            "post_type": [
                "page"
            ],
            "post_status": [
                "publish",
                "draft"
            ],
            "allow_null": 1,
            "multiple": 0,
            "allow_archives": 0,
            "taxonomy": []
        },
        {
            "key": "field_society_initiatives_card_style",
            "label": "Card emphasis",
            "name": "society_initiatives_card_style",
            "aria-label": "",
            "type": "button_group",
            "instructions": "Visual hint for template logic. Useful if one initiative should be highlighted.",
            "required": 0,
            "conditional_logic": 0,
            "wrapper": {
                "width": "50",
                "class": "",
                "id": ""
            },
            "choices": {
                "balanced": "Balanced grid",
                "featured_first": "Featured first card"
            },
            "default_value": "balanced",
            "return_format": "value",
            "allow_null": 0,
            "layout": "horizontal"
        },
        {
            "key": "field_society_landing_tab_media",
            "label": "Media",
            "name": "",
            "aria-label": "",
            "type": "tab",
            "instructions": "",
            "required": 0,
            "conditional_logic": 0,
            "wrapper": {
                "width": "",
                "class": "",
                "id": ""
            },
            "placement": "top",
            "endpoint": 0,
            "selected": 0
        },
        {
            "key": "field_society_media_title",
            "label": "Section title",
            "name": "society_media_title",
            "aria-label": "",
            "type": "text",
            "instructions": "Recommended label: Podcasty i infografiki.",
            "required": 0,
            "conditional_logic": 0,
            "wrapper": {
                "width": "50",
                "class": "",
                "id": ""
            },
            "default_value": "Podcasty i infografiki",
            "maxlength": 120,
            "allow_in_bindings": 0,
            "placeholder": "",
            "prepend": "",
            "append": ""
        },
        {
            "key": "field_society_media_intro",
            "label": "Section intro",
            "name": "society_media_intro",
            "aria-label": "",
            "type": "textarea",
            "instructions": "Optional intro for the media block.",
            "required": 0,
            "conditional_logic": 0,
            "wrapper": {
                "width": "50",
                "class": "",
                "id": ""
            },
            "default_value": "",
            "maxlength": "",
            "rows": 2,
            "placeholder": "",
            "new_lines": "br"
        },
        {
            "key": "field_society_media_mode",
            "label": "Content mode",
            "name": "society_media_mode",
            "aria-label": "",
            "type": "button_group",
            "instructions": "Choose whether this block uses manual selection or latest filtered posts.",
            "required": 0,
            "conditional_logic": 0,
            "wrapper": {
                "width": "34",
                "class": "",
                "id": ""
            },
            "choices": {
                "manual": "Manual selection",
                "latest": "Latest posts"
            },
            "default_value": "manual",
            "return_format": "value",
            "allow_null": 0,
            "layout": "horizontal"
        },
        {
            "key": "field_society_media_count",
            "label": "Number of cards",
            "name": "society_media_count",
            "aria-label": "",
            "type": "number",
            "instructions": "Recommended: 3 or 4.",
            "required": 0,
            "conditional_logic": 0,
            "wrapper": {
                "width": "33",
                "class": "",
                "id": ""
            },
            "default_value": 3,
            "min": 1,
            "max": 12,
            "step": 1,
            "placeholder": "",
            "prepend": "",
            "append": ""
        },
        {
            "key": "field_society_media_archive_page",
            "label": "Archive \/ all media page",
            "name": "society_media_archive_page",
            "aria-label": "",
            "type": "page_link",
            "instructions": "Optional destination for ‘view all’ button.",
            "required": 0,
            "conditional_logic": 0,
            "wrapper": {
                "width": "33",
                "class": "",
                "id": ""
            },
            "post_type": [
                "page"
            ],
            "post_status": [
                "publish",
                "draft"
            ],
            "allow_null": 1,
            "multiple": 0,
            "allow_archives": 0,
            "taxonomy": []
        },
        {
            "key": "field_society_media_manual_posts",
            "label": "Manual media posts",
            "name": "society_media_manual_posts",
            "aria-label": "",
            "type": "relationship",
            "instructions": "Select podcast \/ infographic \/ media posts to feature.",
            "required": 0,
            "conditional_logic": [
                [
                    {
                        "field": "field_society_media_mode",
                        "operator": "==",
                        "value": "manual"
                    }
                ]
            ],
            "wrapper": {
                "width": "100",
                "class": "",
                "id": ""
            },
            "post_type": [
                "post"
            ],
            "post_status": [
                "publish",
                "draft"
            ],
            "taxonomy": "",
            "filters": [
                "search",
                "post_type",
                "taxonomy"
            ],
            "return_format": "object",
            "min": 0,
            "max": 12,
            "elements": [
                "featured_image"
            ],
            "bidirectional_target": []
        },
        {
            "key": "field_society_landing_tab_meet_us",
            "label": "Meet us",
            "name": "",
            "aria-label": "",
            "type": "tab",
            "instructions": "",
            "required": 0,
            "conditional_logic": 0,
            "wrapper": {
                "width": "",
                "class": "",
                "id": ""
            },
            "placement": "top",
            "endpoint": 0,
            "selected": 0
        },
        {
            "key": "field_society_meet_us_title",
            "label": "Section title",
            "name": "society_meet_us_title",
            "aria-label": "",
            "type": "text",
            "instructions": "",
            "required": 0,
            "conditional_logic": 0,
            "wrapper": {
                "width": "50",
                "class": "",
                "id": ""
            },
            "default_value": "Spotkaj się z nami",
            "maxlength": 120,
            "allow_in_bindings": 0,
            "placeholder": "",
            "prepend": "",
            "append": ""
        },
        {
            "key": "field_society_meet_us_intro",
            "label": "Section intro",
            "name": "society_meet_us_intro",
            "aria-label": "",
            "type": "textarea",
            "instructions": "Optional short introduction.",
            "required": 0,
            "conditional_logic": 0,
            "wrapper": {
                "width": "50",
                "class": "",
                "id": ""
            },
            "default_value": "",
            "maxlength": "",
            "rows": 2,
            "placeholder": "",
            "new_lines": "br"
        },
        {
            "key": "field_society_meet_us_cards",
            "label": "Meet us cards",
            "name": "society_meet_us_cards",
            "aria-label": "",
            "type": "repeater",
            "instructions": "Recommended cards: Spotkania edukacyjne, Zajęcia w labach, Warsztaty w terenie.",
            "required": 0,
            "conditional_logic": 0,
            "wrapper": {
                "width": "100",
                "class": "",
                "id": ""
            },
            "layout": "row",
            "pagination": 0,
            "min": 0,
            "max": 6,
            "collapsed": "field_society_meet_us_card_title",
            "button_label": "Add card",
            "rows_per_page": 20,
            "sub_fields": [
                {
                    "key": "field_society_meet_us_card_title",
                    "label": "Title",
                    "name": "title",
                    "aria-label": "",
                    "type": "text",
                    "instructions": "",
                    "required": false,
                    "conditional_logic": false,
                    "wrapper": {
                        "width": "30",
                        "class": "",
                        "id": ""
                    },
                    "maxlength": 120,
                    "allow_in_bindings": 0,
                    "default_value": "",
                    "placeholder": "",
                    "prepend": "",
                    "append": "",
                    "parent_repeater": "field_society_meet_us_cards"
                },
                {
                    "key": "field_society_meet_us_card_text",
                    "label": "Text",
                    "name": "text",
                    "aria-label": "",
                    "type": "textarea",
                    "instructions": "",
                    "required": false,
                    "conditional_logic": false,
                    "wrapper": {
                        "width": "40",
                        "class": "",
                        "id": ""
                    },
                    "rows": 3,
                    "new_lines": "br",
                    "default_value": "",
                    "maxlength": "",
                    "placeholder": "",
                    "parent_repeater": "field_society_meet_us_cards"
                },
                {
                    "key": "field_society_meet_us_card_link_mode",
                    "label": "Link type",
                    "name": "link_mode",
                    "aria-label": "",
                    "type": "button_group",
                    "instructions": "",
                    "required": false,
                    "conditional_logic": false,
                    "wrapper": {
                        "width": "15",
                        "class": "",
                        "id": ""
                    },
                    "choices": {
                        "page": "Page",
                        "url": "Custom URL"
                    },
                    "default_value": "page",
                    "return_format": "value",
                    "layout": "horizontal",
                    "allow_null": 0,
                    "parent_repeater": "field_society_meet_us_cards"
                },
                {
                    "key": "field_society_meet_us_card_page",
                    "label": "Page",
                    "name": "page",
                    "aria-label": "",
                    "type": "page_link",
                    "instructions": "",
                    "required": false,
                    "conditional_logic": [
                        [
                            {
                                "field": "field_society_meet_us_card_link_mode",
                                "operator": "==",
                                "value": "page"
                            }
                        ]
                    ],
                    "wrapper": {
                        "width": "15",
                        "class": "",
                        "id": ""
                    },
                    "post_type": [
                        "page"
                    ],
                    "post_status": [
                        "publish",
                        "draft"
                    ],
                    "allow_null": 1,
                    "multiple": 0,
                    "allow_archives": 0,
                    "taxonomy": [],
                    "parent_repeater": "field_society_meet_us_cards"
                },
                {
                    "key": "field_society_meet_us_card_url",
                    "label": "Custom URL",
                    "name": "url",
                    "aria-label": "",
                    "type": "url",
                    "instructions": "",
                    "required": false,
                    "conditional_logic": [
                        [
                            {
                                "field": "field_society_meet_us_card_link_mode",
                                "operator": "==",
                                "value": "url"
                            }
                        ]
                    ],
                    "wrapper": {
                        "width": "15",
                        "class": "",
                        "id": ""
                    },
                    "default_value": "",
                    "placeholder": "",
                    "parent_repeater": "field_society_meet_us_cards"
                }
            ]
        },
        {
            "key": "field_society_meet_us_form_shortcode",
            "label": "Form shortcode",
            "name": "society_meet_us_form_shortcode",
            "aria-label": "",
            "type": "text",
            "instructions": "Optional form shown directly on landing or linked page.",
            "required": 0,
            "conditional_logic": 0,
            "wrapper": {
                "width": "50",
                "class": "",
                "id": ""
            },
            "default_value": "",
            "maxlength": 255,
            "allow_in_bindings": 0,
            "placeholder": "[forminator_form id=\"123\"]",
            "prepend": "",
            "append": ""
        },
        {
            "key": "field_society_meet_us_form_note",
            "label": "Form note",
            "name": "society_meet_us_form_note",
            "aria-label": "",
            "type": "textarea",
            "instructions": "Optional note above the form.",
            "required": 0,
            "conditional_logic": 0,
            "wrapper": {
                "width": "50",
                "class": "",
                "id": ""
            },
            "default_value": "",
            "rows": 2,
            "new_lines": "br",
            "maxlength": "",
            "placeholder": ""
        },
        {
            "key": "field_society_landing_tab_schools",
            "label": "Schools",
            "name": "",
            "aria-label": "",
            "type": "tab",
            "instructions": "",
            "required": 0,
            "conditional_logic": 0,
            "wrapper": {
                "width": "",
                "class": "",
                "id": ""
            },
            "placement": "top",
            "endpoint": 0,
            "selected": 0
        },
        {
            "key": "field_society_schools_title",
            "label": "Section title",
            "name": "society_schools_title",
            "aria-label": "",
            "type": "text",
            "instructions": "",
            "required": 0,
            "conditional_logic": 0,
            "wrapper": {
                "width": "50",
                "class": "",
                "id": ""
            },
            "default_value": "Dla szkół",
            "maxlength": 120,
            "allow_in_bindings": 0,
            "placeholder": "",
            "prepend": "",
            "append": ""
        },
        {
            "key": "field_society_schools_page",
            "label": "Optional full page",
            "name": "society_schools_page",
            "aria-label": "",
            "type": "page_link",
            "instructions": "Optional dedicated page for schools.",
            "required": 0,
            "conditional_logic": 0,
            "wrapper": {
                "width": "50",
                "class": "",
                "id": ""
            },
            "post_type": [
                "page"
            ],
            "post_status": [
                "publish",
                "draft"
            ],
            "allow_null": 1,
            "multiple": 0,
            "allow_archives": 0,
            "taxonomy": []
        },
        {
            "key": "field_society_schools_content",
            "label": "Content",
            "name": "society_schools_content",
            "aria-label": "",
            "type": "wysiwyg",
            "instructions": "Text for schools and educational partners.",
            "required": 0,
            "conditional_logic": 0,
            "wrapper": {
                "width": "65",
                "class": "",
                "id": ""
            },
            "default_value": "",
            "tabs": "all",
            "toolbar": "full",
            "media_upload": 1,
            "delay": 0
        },
        {
            "key": "field_society_schools_form_shortcode",
            "label": "Form shortcode",
            "name": "society_schools_form_shortcode",
            "aria-label": "",
            "type": "text",
            "instructions": "E.g. sign-up form for school mailing base.",
            "required": 0,
            "conditional_logic": 0,
            "wrapper": {
                "width": "35",
                "class": "",
                "id": ""
            },
            "default_value": "",
            "maxlength": 255,
            "allow_in_bindings": 0,
            "placeholder": "[forminator_form id=\"123\"]",
            "prepend": "",
            "append": ""
        },
        {
            "key": "field_society_landing_tab_cta",
            "label": "Final CTA",
            "name": "",
            "aria-label": "",
            "type": "tab",
            "instructions": "",
            "required": 0,
            "conditional_logic": 0,
            "wrapper": {
                "width": "",
                "class": "",
                "id": ""
            },
            "placement": "top",
            "endpoint": 0,
            "selected": 0
        },
        {
            "key": "field_society_final_cta_enabled",
            "label": "Show final CTA",
            "name": "society_final_cta_enabled",
            "aria-label": "",
            "type": "true_false",
            "instructions": "",
            "required": 0,
            "conditional_logic": 0,
            "wrapper": {
                "width": "25",
                "class": "",
                "id": ""
            },
            "message": "Enable final CTA block",
            "default_value": 1,
            "ui": 1,
            "ui_on_text": "Show",
            "ui_off_text": "Hide"
        },
        {
            "key": "field_society_final_cta_title",
            "label": "Title",
            "name": "society_final_cta_title",
            "aria-label": "",
            "type": "text",
            "instructions": "",
            "required": 0,
            "conditional_logic": [
                [
                    {
                        "field": "field_society_final_cta_enabled",
                        "operator": "==",
                        "value": "1"
                    }
                ]
            ],
            "wrapper": {
                "width": "75",
                "class": "",
                "id": ""
            },
            "default_value": "Skontaktuj się z nami",
            "maxlength": 120,
            "allow_in_bindings": 0,
            "placeholder": "",
            "prepend": "",
            "append": ""
        },
        {
            "key": "field_society_final_cta_text",
            "label": "Text",
            "name": "society_final_cta_text",
            "aria-label": "",
            "type": "textarea",
            "instructions": "",
            "required": 0,
            "conditional_logic": [
                [
                    {
                        "field": "field_society_final_cta_enabled",
                        "operator": "==",
                        "value": "1"
                    }
                ]
            ],
            "wrapper": {
                "width": "65",
                "class": "",
                "id": ""
            },
            "default_value": "",
            "rows": 3,
            "new_lines": "br",
            "maxlength": "",
            "placeholder": ""
        },
        {
            "key": "field_society_final_cta_button",
            "label": "Button",
            "name": "society_final_cta_button",
            "aria-label": "",
            "type": "group",
            "instructions": "",
            "required": 0,
            "conditional_logic": [
                [
                    {
                        "field": "field_society_final_cta_enabled",
                        "operator": "==",
                        "value": "1"
                    }
                ]
            ],
            "wrapper": {
                "width": "35",
                "class": "",
                "id": ""
            },
            "layout": "block",
            "sub_fields": [
                {
                    "key": "field_society_final_cta_button_label",
                    "label": "Label",
                    "name": "label",
                    "aria-label": "",
                    "type": "text",
                    "instructions": "",
                    "required": false,
                    "conditional_logic": false,
                    "wrapper": {
                        "width": "50",
                        "class": "",
                        "id": ""
                    },
                    "maxlength": 60,
                    "allow_in_bindings": 0,
                    "default_value": "",
                    "placeholder": "",
                    "prepend": "",
                    "append": ""
                },
                {
                    "key": "field_society_final_cta_button_url",
                    "label": "URL",
                    "name": "url",
                    "aria-label": "",
                    "type": "url",
                    "instructions": "",
                    "required": false,
                    "conditional_logic": false,
                    "wrapper": {
                        "width": "50",
                        "class": "",
                        "id": ""
                    },
                    "default_value": "",
                    "placeholder": ""
                }
            ]
        }
    ],
    "location": [
        [
            {
                "param": "page_template",
                "operator": "==",
                "value": "page-templates\/template-society.php"
            }
        ]
    ],
    "menu_order": 0,
    "position": "normal",
    "style": "default",
    "label_placement": "top",
    "instruction_placement": "label",
    "hide_on_screen": "",
    "active": false,
    "description": "Fields for the main Society landing page.",
    "show_in_rest": 0,
    "display_title": "",
    "allow_ai_access": false,
    "ai_description": "",
    "modified": 1776678346
}
